memory/__init__.py
memory/__main__.py
memory_oc-1.0.1.dist-info/METADATA
memory_oc-1.0.1.dist-info/WHEEL
memory_oc-1.0.1.dist-info/licenses/LICENSE
memory_oc-1.0.1.dist-info/RECORD
